LICENSE
MANIFEST.in
README
setup.py
src/sleipnir/__init__.py
src/sleipnir.heuristics.egg-info/PKG-INFO
src/sleipnir.heuristics.egg-info/SOURCES.txt
src/sleipnir.heuristics.egg-info/dependency_links.txt
src/sleipnir.heuristics.egg-info/namespace_packages.txt
src/sleipnir.heuristics.egg-info/not-zip-safe
src/sleipnir.heuristics.egg-info/requires.txt
src/sleipnir.heuristics.egg-info/top_level.txt
src/sleipnir/heuristics/__init__.py
src/sleipnir/heuristics/constants.py
src/sleipnir/heuristics/evaluators.py
src/sleipnir/heuristics/exceptions.py
src/sleipnir/heuristics/locations.py
src/sleipnir/heuristics/routes.py
src/sleipnir/heuristics/sections.py
src/sleipnir/heuristics/solutions.py
src/sleipnir/heuristics/helpers/__init__.py
src/sleipnir/heuristics/helpers/marshal.py
src/sleipnir/heuristics/helpers/problem.py
src/sleipnir/heuristics/helpers/solver.py
src/sleipnir/heuristics/interfaces/__init__.py
src/sleipnir/heuristics/interfaces/marshal.py
src/sleipnir/heuristics/interfaces/problem.py
src/sleipnir/heuristics/interfaces/solver.py
src/sleipnir/heuristics/tests/__init__.py
src/sleipnir/heuristics/tests/test_sections.py
src/sleipnir/heuristics/tests/test_solver.py